RequestsQIWI
