Metadata-Version: 1.0
Name: RequestsQIWI
Version: 0.3
Summary: QIWI API for Humans
Home-page: https://github.com/YolSolo/RequestsQIWI
Author: YolSolo
Author-email: aenshtein49@gmail.com
License: UNKNOWN
Platform: UNKNOWN
